proto_square_api/__init__.py
proto_square_api/squareup_pb2.py
proto_square_api/squareup_pb2_twirp.py
proto_square_api-0.1.0.dist-info/WHEEL
proto_square_api-0.1.0.dist-info/METADATA
proto_square_api-0.1.0.dist-info/RECORD
