Metadata-Version: 2.1
Name: proto-square-api
Version: 0.1.0
Summary: 
Author: Jerome Leclanche
Author-email: jerome@leclan.ch
Requires-Python: >=3.8,<4.0
Classifier: Programming Language :: Python :: 3
Classifier: Programming Language :: Python :: 3.8
Requires-Dist: protobuf (>=3.11.3,<4.0.0)
